{
  "version": 4,
  "items": [
    {
      "id": "euskadi",
      "title": "Euskadi"
    },
    {
      "id": "madrid",
      "title": "Madrid"
    },
    {
      "id": "andalucia",
      "title": "Andalucía"
    },
    {
      "id": "catalunya",
      "title": "Cataluña"
    },
    {
      "id": "galicia",
      "title": "Galicia"
    },
    {
      "id": "comunitat_valenciana",
      "title": "Comunitat Valenciana"
    },
    {
      "id": "canarias",
      "title": "Canarias"
    },
    {
      "id": "castilla_y_leon",
      "title": "Castilla y León"
    },
    {
      "id": "aragon",
      "title": "Aragón"
    },
    {
      "id": "asturias",
      "title": "Asturias"
    },
    {
      "id": "cantabria",
      "title": "Cantabria"
    },
    {
      "id": "murcia",
      "title": "Murcia"
    },
    {
      "id": "navarra",
      "title": "Navarra"
    },
    {
      "id": "la_rioja",
      "title": "La Rioja"
    },
    {
      "id": "extremadura",
      "title": "Extremadura"
    },
    {
      "id": "castilla_la_mancha",
      "title": "Castilla-La Mancha"
    },
    {
      "id": "illes_balears",
      "title": "Illes Balears"
    }
  ]
}
